LICENSE
MANIFEST.in
README.md
setup.py
django_continue_reading/__init__.py
django_continue_reading/models.py
django_continue_reading/views.py
django_continue_reading.egg-info/PKG-INFO
django_continue_reading.egg-info/SOURCES.txt
django_continue_reading.egg-info/dependency_links.txt
django_continue_reading.egg-info/top_level.txt
django_continue_reading/templates/django_continue_reading/templatetags/continue_reading.html
django_continue_reading/templatetags/__init__.py
django_continue_reading/templatetags/continue_reading.py
django_continue_reading/tests/__init__.py
django_continue_reading/tests/models.py
django_continue_reading/tests/runtests.py
django_continue_reading/tests/test_settings.py
django_continue_reading/tests/tests.py
django_continue_reading/tests/urls.py
django_continue_reading/tests/views.py