Metadata-Version: 1.0
Name: django-continue-reading
Version: 0.1.1
Summary: Templatetag for truncating blog post bodies...
Home-page: https://github.com/cloverchio/django-continue-reading
Author: Chris Loverchio
Author-email: chrisloverchio@gmail.com
License: MIT
Keywords: django,app,reusable,blog,posts,links,module
Platform: UNKNOWN
